contributor_1/__init__.py
contributor_1/app.py
contributor_1/app_query_engine.py
contributor_1-0.2.1.dist-info/METADATA
contributor_1-0.2.1.dist-info/WHEEL
contributor_1-0.2.1.dist-info/RECORD
