Metadata-Version: 2.4
Name: contributor-1
Version: 0.2.1
Author-email: Your Name <you@example.com>
Requires-Python: <4.0,>=3.9
Requires-Dist: llama-index-llms-openai<0.5,>=0.4.0
Requires-Dist: llama-index-networks<0.6,>=0.5.1
Requires-Dist: llama-index<0.13,>=0.12.0
